{
  "source": "GUS BDL, subject P2635 (Wydatki w Dziale 600 — Transport i łączność, MnPP)",
  "unit": "Gdańsk (042214361000)",
  "definitions": {
    "roads_pln": "rozdz. 60015 + 60016 (city + gmina public roads, build + maintain)",
    "nonroad_transport_pln": "dział-600 total − all road chapters ≈ public transport (ZTM bus/tram) + rail (SKM/PKM) + misc",
    "current_pln": "wydatki bieżące ogółem (operating + maintenance, incl. road repairs)",
    "capital_pln": "wydatki majątkowe ogółem (investment / building)"
  },
  "years": {
    "2004": {
      "total_pln": 209949331,
      "roads_pln": 0,
      "roads_all_pln": null,
      "nonroad_transport_pln": 209949331,
      "current_pln": 0,
      "capital_pln": 41751869,
      "pop": 459072,
      "roads_per_cap": 0.0,
      "nonroad_per_cap": 457.3,
      "roads_share": 0.0
    },
    "2005": {
      "total_pln": 240052103,
      "roads_pln": 0,
      "roads_all_pln": null,
      "nonroad_transport_pln": 240052103,
      "current_pln": 0,
      "capital_pln": 54770922,
      "pop": 458053,
      "roads_per_cap": 0.0,
      "nonroad_per_cap": 524.1,
      "roads_share": 0.0
    },
    "2006": {
      "total_pln": 352201797,
      "roads_pln": 0,
      "roads_all_pln": null,
      "nonroad_transport_pln": 352201797,
      "current_pln": 0,
      "capital_pln": 156807472,
      "pop": 456658,
      "roads_per_cap": 0.0,
      "nonroad_per_cap": 771.3,
      "roads_share": 0.0
    },
    "2007": {
      "total_pln": 457921487,
      "roads_pln": 0,
      "roads_all_pln": null,
      "nonroad_transport_pln": 457921487,
      "current_pln": 0,
      "capital_pln": 246052078,
      "pop": 455717,
      "roads_per_cap": 0.0,
      "nonroad_per_cap": 1004.8,
      "roads_share": 0.0
    },
    "2008": {
      "total_pln": 355814829,
      "roads_pln": 0,
      "roads_all_pln": 142110601,
      "nonroad_transport_pln": 213704228,
      "current_pln": 228695832,
      "capital_pln": 127118997,
      "pop": 455581,
      "roads_per_cap": 0.0,
      "nonroad_per_cap": 469.1,
      "roads_share": 0.0
    },
    "2009": {
      "total_pln": 379026699,
      "roads_pln": 0,
      "roads_all_pln": 160268087,
      "nonroad_transport_pln": 218758613,
      "current_pln": 258189601,
      "capital_pln": 120837098,
      "pop": 456591,
      "roads_per_cap": 0.0,
      "nonroad_per_cap": 479.1,
      "roads_share": 0.0
    },
    "2010": {
      "total_pln": 540233435,
      "roads_pln": 0,
      "roads_all_pln": 238058168,
      "nonroad_transport_pln": 302175267,
      "current_pln": 278394791,
      "capital_pln": 261838644,
      "pop": 460509,
      "roads_per_cap": 0.0,
      "nonroad_per_cap": 656.2,
      "roads_share": 0.0
    },
    "2011": {
      "total_pln": 898824702,
      "roads_pln": 0,
      "roads_all_pln": 465475986,
      "nonroad_transport_pln": 433348715,
      "current_pln": 306365829,
      "capital_pln": 592458872,
      "pop": 460517,
      "roads_per_cap": 0.0,
      "nonroad_per_cap": 941.0,
      "roads_share": 0.0
    },
    "2012": {
      "total_pln": 1162287780,
      "roads_pln": 809941484,
      "roads_all_pln": null,
      "nonroad_transport_pln": 352346296,
      "current_pln": 344767925,
      "capital_pln": 817519855,
      "pop": 460427,
      "roads_per_cap": 1759.1,
      "nonroad_per_cap": 765.3,
      "roads_share": 69.7
    },
    "2013": {
      "total_pln": 902677312,
      "roads_pln": 594654852,
      "roads_all_pln": null,
      "nonroad_transport_pln": 308022460,
      "current_pln": 358360034,
      "capital_pln": 544317278,
      "pop": 461531,
      "roads_per_cap": 1288.4,
      "nonroad_per_cap": 667.4,
      "roads_share": 65.9
    },
    "2014": {
      "total_pln": 766696152,
      "roads_pln": 390108401,
      "roads_all_pln": null,
      "nonroad_transport_pln": 376587751,
      "current_pln": 345083915,
      "capital_pln": 421612237,
      "pop": 461489,
      "roads_per_cap": 845.3,
      "nonroad_per_cap": 816.0,
      "roads_share": 50.9
    },
    "2015": {
      "total_pln": 662259937,
      "roads_pln": 240899870,
      "roads_all_pln": null,
      "nonroad_transport_pln": 421360067,
      "current_pln": 351000763,
      "capital_pln": 311259174,
      "pop": 462249,
      "roads_per_cap": 521.1,
      "nonroad_per_cap": 911.5,
      "roads_share": 36.4
    },
    "2016": {
      "total_pln": 560337297,
      "roads_pln": 257157676,
      "roads_all_pln": null,
      "nonroad_transport_pln": 303179621,
      "current_pln": 350584808,
      "capital_pln": 209752488,
      "pop": 463754,
      "roads_per_cap": 554.5,
      "nonroad_per_cap": 653.8,
      "roads_share": 45.9
    },
    "2017": {
      "total_pln": 491872927,
      "roads_pln": 176023496,
      "roads_all_pln": null,
      "nonroad_transport_pln": 315849432,
      "current_pln": 367948250,
      "capital_pln": 123924677,
      "pop": 464254,
      "roads_per_cap": 379.2,
      "nonroad_per_cap": 680.3,
      "roads_share": 35.8
    },
    "2018": {
      "total_pln": 686688401,
      "roads_pln": 202205869,
      "roads_all_pln": null,
      "nonroad_transport_pln": 484482531,
      "current_pln": 393404477,
      "capital_pln": 293283923,
      "pop": 466631,
      "roads_per_cap": 433.3,
      "nonroad_per_cap": 1038.3,
      "roads_share": 29.4
    },
    "2019": {
      "total_pln": 822593598,
      "roads_pln": 223230071,
      "roads_all_pln": null,
      "nonroad_transport_pln": 599363527,
      "current_pln": 520500653,
      "capital_pln": 302092946,
      "pop": 470907,
      "roads_per_cap": 474.0,
      "nonroad_per_cap": 1272.8,
      "roads_share": 27.1
    },
    "2020": {
      "total_pln": 806096725,
      "roads_pln": 212815544,
      "roads_all_pln": null,
      "nonroad_transport_pln": 593281181,
      "current_pln": 472851453,
      "capital_pln": 333245272,
      "pop": 486542,
      "roads_per_cap": 437.4,
      "nonroad_per_cap": 1219.4,
      "roads_share": 26.4
    },
    "2021": {
      "total_pln": 718650016,
      "roads_pln": 202868965,
      "roads_all_pln": null,
      "nonroad_transport_pln": 515781051,
      "current_pln": 544523754,
      "capital_pln": 174126262,
      "pop": 486271,
      "roads_per_cap": 417.2,
      "nonroad_per_cap": 1060.7,
      "roads_share": 28.2
    },
    "2022": {
      "total_pln": 836278322,
      "roads_pln": 191729385,
      "roads_all_pln": null,
      "nonroad_transport_pln": 644548937,
      "current_pln": 658359339,
      "capital_pln": 177918983,
      "pop": 486345,
      "roads_per_cap": 394.2,
      "nonroad_per_cap": 1325.3,
      "roads_share": 22.9
    },
    "2023": {
      "total_pln": 846980530,
      "roads_pln": 180785350,
      "roads_all_pln": null,
      "nonroad_transport_pln": 666195180,
      "current_pln": 675520043,
      "capital_pln": 171460487,
      "pop": 487371,
      "roads_per_cap": 370.9,
      "nonroad_per_cap": 1366.9,
      "roads_share": 21.3
    },
    "2024": {
      "total_pln": 969902427,
      "roads_pln": 238731915,
      "roads_all_pln": null,
      "nonroad_transport_pln": 731170512,
      "current_pln": 759113984,
      "capital_pln": 210788443,
      "pop": 488651,
      "roads_per_cap": 488.6,
      "nonroad_per_cap": 1496.3,
      "roads_share": 24.6
    }
  }
}